dolreader/__init__.py
dolreader/dol.py
dolreader/dolfile.py
dolreader/exceptions.py
dolreader/section.py
dolreader-1.1.1.dist-info/LICENSE
dolreader-1.1.1.dist-info/METADATA
dolreader-1.1.1.dist-info/WHEEL
dolreader-1.1.1.dist-info/top_level.txt
dolreader-1.1.1.dist-info/RECORD
